{
  "videoId": "68e2843e66ecb2513d7f0bf4",
  "analysisType": "clip_comprehensive",
  "result": {
    "tiktok": "The video captures a scene inside a modern, minimalist cafe where two individuals, a man and a woman, are seated at separate tables. The man, wearing glasses and a beard, is focused on his laptop, while the woman is using her own device. Both laptops are placed on marble-patterned covers, and each person has a disposable coffee cup in front of them. Their black backpacks are positioned beside them against the wall. The cafe's transparent walls allow a view of other patrons engaged in conversation in the larger space beyond. The video does not feature any specific brands or products, and the main message seems to revolve around the casual and relaxed atmosphere of the cafe. The audio includes a dialogue where the man mentions he will match someone in general once he is good with his voice-over script, suggesting a theme related to voice-over work or a similar activity. The overall narrative is straightforward, depicting a typical scene of people working in a modern cafe setting.",
    "instagram": "The video showcases a modern and stylish cafe setting, with a clean and minimalistic visual style. The color palette is neutral, dominated by whites and grays, which creates a calm and professional atmosphere. The lighting is soft and natural, enhancing the aesthetic quality and providing a warm ambiance. The composition is well-balanced, with a glass wall offering a clear view into the cafe, while the foreground features two individuals at a table, emphasizing a sense of focus and productivity.\n\nIn terms of fashion and styling, the individuals are dressed in casual yet neat attire, aligning with the contemporary and relaxed vibe of the cafe. The design elements, such as the sleek furniture and the organized layout, contribute to the Instagram-worthy aesthetic. The scene captures a moment of concentration and collaboration, making it visually appealing and relatable for social media audiences.\n\nThe lifestyle theme presented revolves around productivity and creativity, as the individuals are engaged in work on their laptops. This aspirational element resonates with viewers who value a balanced and focused work environment. The behind-the-scenes aspect of the video, showing the everyday life of professionals, adds authenticity and relatability, appealing to a wide audience.\n\nBrand presentation is subtle yet effective, with the cafe's interior design and the individuals' use of laptops subtly showcasing the brands involved. The integration is natural, without overt promotion, allowing the viewer to appreciate the setting and the activities taking place. The brand messaging is implied through the professional and creative atmosphere, positioning the cafe as a hub for innovation and productivity.\n\nThe content flow is smooth and coherent, with the narrative unfolding seamlessly from the initial focus on the individuals to the broader view of the cafe. Key story beats include the transition from the close-up of the individuals to the wider shot of the cafe, highlighting the connection between personal work and the communal space. The transitions are fluid, maintaining a consistent mood and tone throughout the video.\n\nAudio elements, such as background music, likely complement the visual content, enhancing the mood and tone. The spoken content, which mentions matching someone in general when the voice-over script is good, aligns with the professional and creative theme, reinforcing the brand's message. Overall, the video effectively combines visual aesthetics, lifestyle elements, and brand presentation, making it suitable for Instagram content potential."
  },
  "timestamp": "2025-10-07T13:09:31.495Z"
}